nordlys_py/__init__.py
nordlys_py/client.py
nordlys_py/errors.py
nordlys_py/models.py
nordlys_py/py.typed
nordlys_py/registry.py
nordlys_py/router.py
nordlys_py-0.1.0.dist-info/WHEEL
nordlys_py-0.1.0.dist-info/METADATA
nordlys_py-0.1.0.dist-info/RECORD
