Metadata-Version: 2.3
Name: nordlys-py
Version: 0.1.0
Summary: Python client SDK for Nordlys intelligent model selection service
Author: Botir Khaltaev
Author-email: Botir Khaltaev <btrghstk@gmail.com>
Requires-Dist: httpx>=0.27.0
Requires-Dist: openai>=1.40.0
Requires-Dist: pydantic>=2.12.5
Requires-Python: >=3.12
